gleipnir/__init__.py
gleipnir/distributions.py
gleipnir/dnest4.py
gleipnir/dypolychord.py
gleipnir/multinest.py
gleipnir/nested_sampling.py
gleipnir/nestle.py
gleipnir/nsbase.py
gleipnir/polychord.py
gleipnir/sampled_parameter.py
gleipnir/sampler_setup.py
gleipnir/samplers.py
gleipnir/stopping_criterion.py
gleipnir/nestedsampling/__init__.py
gleipnir/nestedsampling/nested_sampling.py
gleipnir/nestedsampling/samplers.py
gleipnir/nestedsampling/stopping_criterion.py
gleipnir/pysb_utilities/__init__.py
gleipnir/pysb_utilities/hyp_selector.py
gleipnir/pysb_utilities/model_selector.py
gleipnir/pysb_utilities/nestedsample_it.py
gleipnir/utilities/__init__.py
gleipnir/utilities/knn_entropy.py
gleipnir_ns-0.25.0.dist-info/LICENSE
gleipnir_ns-0.25.0.dist-info/METADATA
gleipnir_ns-0.25.0.dist-info/WHEEL
gleipnir_ns-0.25.0.dist-info/top_level.txt
gleipnir_ns-0.25.0.dist-info/RECORD
