Metadata-Version: 2.1
Name: gleipnir-ns
Version: 0.25.0
Summary: Python toolkit for Nested Sampling.
Home-page: https://github.com/LoLab-VU/Gleipnir
Author: Blake A. Wilson
Author-email: blakeaw1102@gmail.com
License: UNKNOWN
Platform: UNKNOWN
Classifier: Programming Language :: Python :: 3
Classifier: License :: OSI Approved :: MIT License
Classifier: Operating System :: OS Independent
Requires-Python: >=3.6
Requires-Dist: numpy
Requires-Dist: scipy
Requires-Dist: pandas
